flex_cache/__init__.py
flex_cache/basecache.py
flex_cache/diskcache.py
flex_cache/memcache.py
flex_cache/nocache.py
flex_cache/rediscache.py
redis_cache/__init__.py
redis_cache/basecache.py
redis_cache/memcache.py
python_flex_cache-0.1.9.dist-info/LICENSE
python_flex_cache-0.1.9.dist-info/METADATA
python_flex_cache-0.1.9.dist-info/WHEEL
python_flex_cache-0.1.9.dist-info/top_level.txt
python_flex_cache-0.1.9.dist-info/RECORD
