Metadata-Version: 2.1
Name: python-flex-cache
Version: 0.1.9
Summary: Basic Redis/Disk/Memory caching for functions
Home-page: http://github.com/steffenschumacher/python-flex-cache
Author: Steffen Schumacher (forked from python-redis-cache // Taylor Hakes)
Author-email: ssch@wheel.dk
License: MIT
Keywords: redis cache python memory disk
Platform: any
Classifier: Development Status :: 5 - Production/Stable
Classifier: Intended Audience :: Developers
Classifier: License :: OSI Approved :: MIT License
Classifier: Operating System :: OS Independent
Classifier: Topic :: Documentation :: Sphinx
Classifier: Programming Language :: Python
Classifier: Programming Language :: Python :: 3.6
Classifier: Programming Language :: Python :: 3.7
Classifier: Programming Language :: Python :: 3.8
Classifier: Programming Language :: Python :: 3.9
Classifier: Topic :: Software Development :: Libraries :: Python Modules
Requires-Python: >=3.6
License-File: LICENSE
